rest_api_payload/__init__.py
tests/__init__.py
tests/test_init.py
rest_api_payload-0.0.7.dist-info/LICENSE.txt
rest_api_payload-0.0.7.dist-info/METADATA
rest_api_payload-0.0.7.dist-info/WHEEL
rest_api_payload-0.0.7.dist-info/top_level.txt
rest_api_payload-0.0.7.dist-info/RECORD
