Metadata-Version: 2.1
Name: rest-api-payload
Version: 0.0.7
Summary: A to-go-to production API payload with an easy format for building APIs with Python.
Home-page: https://github.com/israelabraham/API-Payload
Author: Abram
Author-email: israelvictory87@gmail.com
License: MIT
Project-URL: Bug Tracker, https://github.com/israelabraham/API-Payload/issues
Keywords: api,payload,custom api payload
Classifier: Development Status :: 5 - Production/Stable
Classifier: Intended Audience :: Education
Classifier: Intended Audience :: Developers
Classifier: License :: OSI Approved :: MIT License
Classifier: Programming Language :: Python :: 3
Requires-Python: >=3
License-File: LICENSE.txt
